Metadata-Version: 1.1
Name: fourdrop-socketio-client
Version: 1.1
Summary: Socket.IO client
Home-page: http://github.com/PeterWunderlich/python-socketio-client/
Author: Peter Wunderlich
Author-email: wunderlich.p@outlook.com
License: MIT
Platform: any
Classifier: Environment :: Web Environment
Classifier: Intended Audience :: Developers
Classifier: License :: OSI Approved :: MIT License
Classifier: Operating System :: OS Independent
Classifier: Programming Language :: Python
Classifier: Programming Language :: Python :: 2
Classifier: Programming Language :: Python :: 3
Classifier: Topic :: Internet :: WWW/HTTP :: Dynamic Content
Classifier: Topic :: Software Development :: Libraries :: Python Modules
